boolgen/__init__.py
boolgen-1.1.0.dist-info/LICENSE.md
boolgen-1.1.0.dist-info/METADATA
boolgen-1.1.0.dist-info/WHEEL
boolgen-1.1.0.dist-info/entry_points.txt
boolgen-1.1.0.dist-info/top_level.txt
boolgen-1.1.0.dist-info/RECORD
