Metadata-Version: 2.1
Name: boolgen
Version: 1.1.0
Summary: A library for generating and simplifying Boolean expressions from truth tables
Home-page: https://github.com/schuyler/boolgen
Author: Schuyler Erle
Author-email: schuyler@nocat.net
Classifier: Programming Language :: Python :: 3
Classifier: License :: OSI Approved :: MIT License
Classifier: Operating System :: OS Independent
Requires-Python: >=3.6
License-File: LICENSE.md
